LICENSE
README.md
stacksearch/__init__.py
stacksearch/__main__.py
stacksearch/errors.py
stacksearch/reverse_markdown.py
stacksearch/search.py
stacksearch-2.dist-info/entry_points.txt
stacksearch-2.dist-info/LICENSE
stacksearch-2.dist-info/WHEEL
stacksearch-2.dist-info/METADATA
stacksearch-2.dist-info/RECORD
