Metadata-Version: 2.1
Name: stacksearch
Version: 2
Summary: StackSearch is a python CLI and library that provides a way to search StackExchange sites.
License: MIT
Keywords: stackexchange,webscrape,api
Author: Bryan Hu
Author-email: bryan.hu.2020@gmail.com
Requires-Python: >=3.6,<4.0
Classifier: Development Status :: 4 - Beta
Classifier: Environment :: Console
Classifier: Intended Audience :: Developers
Classifier: Intended Audience :: End Users/Desktop
Classifier: Intended Audience :: Information Technology
Classifier: Intended Audience :: Science/Research
Classifier: Intended Audience :: System Administrators
Classifier: License :: OSI Approved :: MIT License
Classifier: Natural Language :: English
Classifier: Operating System :: OS Independent
Classifier: Programming Language :: Python :: 3
Classifier: Programming Language :: Python :: 3.6
Classifier: Programming Language :: Python :: 3.7
Classifier: Programming Language :: Python :: 3.8
Classifier: Programming Language :: Python :: 3.9
Classifier: Programming Language :: Python :: Implementation :: CPython
Classifier: Topic :: Utilities
Requires-Dist: aiohttp (>=3.7.3,<4.0.0)
Requires-Dist: beautifulsoup4 (>=4.9.3,<5.0.0)
Requires-Dist: rich (>=9.11.0,<10.0.0)
Project-URL: Documentation, https://stacksearch.readthedocs.io/en/latest/index.html
